shaclapi/__init__.py
shaclapi/api.py
shaclapi/config.py
shaclapi/logger.py
shaclapi/output.py
shaclapi/query.py
shaclapi/statsCalculation.py
shaclapi/triple.py
shaclapi/multiprocessing/PipeAdapter.py
shaclapi/multiprocessing/ThreadEx.py
shaclapi/multiprocessing/__init__.py
shaclapi/multiprocessing/contactSource.py
shaclapi/multiprocessing/functions.py
shaclapi/multiprocessing/runner.py
shaclapi/multiprocessing/Xgjoin/OperatorStructures.py
shaclapi/multiprocessing/Xgjoin/Xgjoin.py
shaclapi/multiprocessing/Xgjoin/__init__.py
shaclapi/multiprocessing/Xgoptional/OperatorStructures.py
shaclapi/multiprocessing/Xgoptional/Xgoptional.py
shaclapi/multiprocessing/Xgoptional/__init__.py
shaclapi/reduction/Reduction.py
shaclapi/reduction/ValidationResultTransmitter.py
shaclapi/reduction/__init__.py
shaclapi/reduction/s2spy/ReducedShapeParser.py
shaclapi/reduction/s2spy/ReducedShapeSchema.py
shaclapi/reduction/s2spy/RuleBasedValidationResultStreaming.py
shaclapi/reduction/s2spy/__init__.py
shaclapi/reduction/travshacl/ReducedShapeParser.py
shaclapi/reduction/travshacl/ReducedShapeSchema.py
shaclapi/reduction/travshacl/ValidationResultStreaming.py
shaclapi/reduction/travshacl/__init__.py
shaclapi-0.12.0.dist-info/LICENSE
shaclapi-0.12.0.dist-info/METADATA
shaclapi-0.12.0.dist-info/WHEEL
shaclapi-0.12.0.dist-info/top_level.txt
shaclapi-0.12.0.dist-info/RECORD
