Metadata-Version: 2.1
Name: shaclapi
Version: 0.12.0
Summary: An API implementing optimizations over SHACL validators.
Home-page: https://github.com/SDM-TIB/shaclAPI
Download-URL: https://github.com/SDM-TIB/shaclAPI/archive/refs/tags/v0.12.0.tar.gz
Author: Julian Gercke, Philipp D. Rohde, Fabian Johannsen
Author-email: philipp.rohde@tib.eu
License: GNU/GPLv3
Classifier: Development Status :: 4 - Beta
Classifier: Programming Language :: Python
Classifier: Programming Language :: Python :: 3
Classifier: Programming Language :: Python :: 3 :: Only
Classifier: Programming Language :: Python :: 3.9
Classifier: Programming Language :: Python :: 3.10
Classifier: Programming Language :: Python :: 3.11
Classifier: Programming Language :: Python :: 3.12
Classifier: License :: OSI Approved :: GNU General Public License v3 (GPLv3)
Classifier: Operating System :: OS Independent
Classifier: Intended Audience :: Science/Research
Requires-Python: >=3.9
License-File: LICENSE
Requires-Dist: SPARQLWrapper >=2.0.0
Requires-Dist: requests >=2.32.0
Requires-Dist: SHACL2SPARQLpy >=1.3.0
Requires-Dist: TravSHACL >=1.9.0
Requires-Dist: multiprocessing-logging >=0.3.1
Requires-Dist: regex >=2022.3.15
